<?xml version="1.0" encoding="UTF-8"?>
<person:delegation xmlns:common="http://www.orcid.org/ns/common"
	xmlns:person="http://www.orcid.org/ns/person" xmlns:personal-details="http://www.orcid.org/ns/personal-details"
	xmlns:other-name="http://www.orcid.org/ns/other-name"
	xmlns:researcher-url="http://www.orcid.org/ns/researcher-url"
	xmlns:email="http://www.orcid.org/ns/email" xmlns:address="http://www.orcid.org/ns/address"
	xmlns:keyword="http://www.orcid.org/ns/keyword"
	xmlns:external-identifier="http://www.orcid.org/ns/external-identifier"
	xmlns:xsi="http://www.w3.org/2001/XMLSchema-instance"
	xsi:schemaLocation="http://www.orcid.org/ns/person ../person-2.0_rc2.xsd ">	
		<person:given-permission-to>
			<person:delegation-details>
				<person:approval-date>2015-12-31T12:00:00</person:approval-date>
				<person:delegate-summary>
					<common:orcid-identifier>
						<common:uri>http://orcid.org/8888-8888-8888-8880</common:uri>
						<common:path>8888-8888-8888-8880</common:path>
						<common:host>orcid.org</common:host>
					</common:orcid-identifier>
					<common:last-modified-date>2016-01-01T12:00:00</common:last-modified-date>
					<person:credit-name visibility="public">credit-name</person:credit-name>
				</person:delegate-summary>
			</person:delegation-details>
		</person:given-permission-to>
		<person:given-permission-by>
			<person:delegation-details>
				<person:approval-date>2015-12-31T12:00:00</person:approval-date>
				<person:delegate-summary>
					<common:orcid-identifier>
						<common:uri>http://orcid.org/8888-8888-8888-8880</common:uri>
						<common:path>8888-8888-8888-8880</common:path>
						<common:host>orcid.org</common:host>
					</common:orcid-identifier>
					<common:last-modified-date>2016-01-01T12:00:00</common:last-modified-date>
					<person:credit-name visibility="public">credit-name</person:credit-name>
				</person:delegate-summary>
			</person:delegation-details>
		</person:given-permission-by>
</person:delegation>	
	